betterproto2_rust_codec-0.1.3.dist-info/METADATA
betterproto2_rust_codec-0.1.3.dist-info/WHEEL
betterproto2_rust_codec-0.1.3.dist-info/licenses/LICENSE
betterproto2_rust_codec.libs/libgcc_s-1e52349c.so.1
betterproto2_rust_codec/__init__.py
betterproto2_rust_codec/__init__.pyi
betterproto2_rust_codec/py.typed
betterproto2_rust_codec/betterproto2_rust_codec.abi3.so
betterproto2_rust_codec-0.1.3.dist-info/RECORD
